CSharpTK/__init__.py
CSharpTK-0.1.dist-info/LICENSE
CSharpTK-0.1.dist-info/METADATA
CSharpTK-0.1.dist-info/WHEEL
CSharpTK-0.1.dist-info/top_level.txt
CSharpTK-0.1.dist-info/RECORD
