Metadata-Version: 2.1
Name: CSharpTK
Version: 0.1
Summary: C# Toolkit
Home-page: https://github.com/xiangqinxi/
Author: XiangQinxi
Author-email: XiangQinxi@outlook.com
License: UNKNOWN
Project-URL: Bug Tracker, https://github.com/xiangqinxi
Platform: UNKNOWN
Classifier: Programming Language :: Python :: 3
Classifier: License :: OSI Approved :: MIT License
Classifier: Operating System :: OS Independent
Requires-Python: >=3.0
License-File: LICENSE
